metis/__init__.py
metis/_api.py
metis/exceptions.py
metis/core/__init__.py
metis/core/evaluator.py
metis/core/orchestrator.py
metis/core/search_space.py
metis/core/trainer.py
metis/models/__init__.py
metis/models/model_factory.py
metis/models/registry.py
metis/quantum/__init__.py
metis/quantum/decoding.py
metis/quantum/encoding.py
metis/quantum/qaoa_sampler.py
metis/utils/__init__.py
metis/utils/data_loader.py
metis/utils/feature_engineering.py
metis_automl-0.1.1.dist-info/licenses/LICENSE
metis_automl-0.1.1.dist-info/METADATA
metis_automl-0.1.1.dist-info/WHEEL
metis_automl-0.1.1.dist-info/top_level.txt
metis_automl-0.1.1.dist-info/RECORD
