Metadata-Version: 2.4
Name: metis-automl
Version: 0.1.1
Summary: Quantum-Enhanced AutoML
Author: Deven Shah
License: MIT
Keywords: automl,machine-learning,quantum-computing
Classifier: Development Status :: 3 - Alpha
Classifier: Intended Audience :: Developers
Classifier: Intended Audience :: Science/Research
Classifier: License :: OSI Approved :: MIT License
Classifier: Programming Language :: Python :: 3
Classifier: Programming Language :: Python :: 3.8
Classifier: Programming Language :: Python :: 3.9
Classifier: Programming Language :: Python :: 3.10
Classifier: Programming Language :: Python :: 3.11
Classifier: Topic :: Scientific/Engineering :: Artificial Intelligence
Classifier: Topic :: Software Development :: Libraries :: Python Modules
Requires-Python: >=3.11
License-File: LICENSE
Requires-Dist: scikit-learn>=1.3.0
Requires-Dist: pandas>=2.0.0
Requires-Dist: numpy>=1.24.0
Requires-Dist: optuna>=3.5.0
Requires-Dist: joblib>=1.3.0
Requires-Dist: xgboost>=2.0.0
Requires-Dist: pennylane>=0.35.0
Requires-Dist: scipy>=1.11.0
Provides-Extra: dev
Requires-Dist: pytest>=7.4.0; extra == "dev"
Requires-Dist: black>=23.0.0; extra == "dev"
Requires-Dist: flake8>=6.0.0; extra == "dev"
Dynamic: license-file
